{
    "@context": [
        "http://iiif.io/api/presentation/2/context.json",
        "http://wellcomelibrary.org/ld/ixif/0/context.json"
    ],
    "@id": "https://dch.iii.u-tokyo.ac.jp/iiif/c970f796-40a4-4da7-8d4d-3909e9b84d48/manifest",
    "@type": "sc:Manifest",
    "attribution": "東京大学大学院情報学環附属社会情報研究資料センター / Multi-media and Socio-Information Studies Archive, Interfaculty Initiative in Information Studies / Graduate School of Interdisciplinary Information Studies",
    "description": "唐人街の決斗",
    "label": "痛快剣道まんが　小天狗小太郎",
    "license": "http://dch.iii.u-tokyo.ac.jp/s/dch/page/license_other",
    "logo": "https://iiif.dl.itc.u-tokyo.ac.jp/images/ut-logo.jpg",
    "metadata": [
        {
            "label": "Title",
            "value": "痛快剣道まんが　小天狗小太郎"
        },
        {
            "label": "Identifier",
            "value": "c970f796-40a4-4da7-8d4d-3909e9b84d48"
        },
        {
            "label": "Sort",
            "value": "OI117"
        },
        {
            "label": "Creator",
            "value": "夢野凡夫"
        },
        {
            "label": "Publisher",
            "value": "集英社"
        },
        {
            "label": "Date",
            "value": "1955-07-01"
        },
        {
            "label": "Publication Volume",
            "value": "7"
        },
        {
            "label": "Number",
            "value": "8"
        },
        {
            "label": "Extent",
            "value": "180×127×7"
        },
        {
            "label": "Is Aggregated By",
            "value": "https://dch.iii.u-tokyo.ac.jp/api/items/61064"
        }
    ],
    "sequences": [
        {
            "@id": "https://dch.iii.u-tokyo.ac.jp/iiif/c970f796-40a4-4da7-8d4d-3909e9b84d48/sequence/normal",
            "@type": "sc:Sequence",
            "canvases": [
                {
                    "@id": "/iiif/ixif-message/canvas/c1",
                    "@type": "sc:Canvas",
                    "height": 200,
                    "images": [
                        {
                            "@id": "/iiif/ixif-message/imageanno/placeholder",
                            "@type": "oa:Annotation",
                            "motivation": "sc:painting",
                            "on": "/iiif/ixif-message/canvas/c1",
                            "resource": {
                                "@id": "/iiif/ixif-message-0/res/placeholder",
                                "@type": "dctypes:Image",
                                "height": 200,
                                "width": 200
                            }
                        }
                    ],
                    "label": "Placeholder image",
                    "thumbnail": "/modules/IiifServer/asset/img/thumbnails/placeholder-image.png?v=3.5.9",
                    "width": 200
                }
            ],
            "compatibilityHint": "displayIfContentUnsupported",
            "label": "Unsupported extension. This manifest is being used as a wrapper for non-IIIF content (e.g., audio, video) and is unfortunately incompatible with IIIF viewers."
        }
    ]
}