{
    "@context": "https://dch.iii.u-tokyo.ac.jp/api-context",
    "@id": "https://dch.iii.u-tokyo.ac.jp/api/items/56365",
    "@type": [
        "o:Item",
        "archiveshub:ArchivalResource"
    ],
    "archiveshub:level": [
        {
            "@value": "アイテム",
            "is_public": true,
            "property_id": 194,
            "property_label": "Level",
            "type": "literal"
        }
    ],
    "bibo:identifier": [
        {
            "@value": "NSKS3-19310716",
            "is_public": true,
            "property_id": 98,
            "property_label": "identifier",
            "type": "literal"
        }
    ],
    "dcndl:volume": [
        {
            "@value": "1117",
            "is_public": true,
            "property_id": 266,
            "property_label": "Volume",
            "type": "literal"
        }
    ],
    "dcterms:extent": [
        {
            "@value": "264×192",
            "is_public": true,
            "property_id": 25,
            "property_label": "Extent",
            "type": "literal"
        }
    ],
    "dcterms:identifier": [
        {
            "@value": "97933bca-e47a-4a65-8d9f-26b6e1163b8e",
            "is_public": true,
            "property_id": 10,
            "property_label": "Identifier",
            "type": "literal"
        }
    ],
    "dcterms:publisher": [
        {
            "@value": "新聞興信所",
            "is_public": true,
            "property_id": 5,
            "property_label": "Publisher",
            "type": "literal"
        }
    ],
    "dcterms:rights": [
        {
            "@id": "http://dch.iii.u-tokyo.ac.jp/s/dch/page/license_shimbun",
            "is_public": true,
            "property_id": 15,
            "property_label": "Rights",
            "type": "uri"
        }
    ],
    "dcterms:title": [
        {
            "@value": "日刊新聞興信所報 1117号",
            "is_public": true,
            "property_id": 1,
            "property_label": "Title",
            "type": "literal"
        }
    ],
    "foaf:thumbnail": [
        {
            "@id": "https://iiif.dl.itc.u-tokyo.ac.jp/iiif/dch/NSKS3_TIFF/NSKS3_0253-1.tif/full/200,200/0/default.jpg",
            "is_public": true,
            "property_id": 157,
            "property_label": "thumbnail",
            "type": "uri"
        }
    ],
    "o:created": {
        "@type": "http://www.w3.org/2001/XMLSchema#dateTime",
        "@value": "2019-04-13T03:51:52+00:00"
    },
    "o:id": 56365,
    "o:is_public": true,
    "o:item_set": [
        {
            "@id": "https://dch.iii.u-tokyo.ac.jp/api/item_sets/53474",
            "o:id": 53474
        },
        {
            "@id": "https://dch.iii.u-tokyo.ac.jp/api/item_sets/61211",
            "o:id": 61211
        }
    ],
    "o:media": [
        {
            "@id": "https://dch.iii.u-tokyo.ac.jp/api/media/58555",
            "o:id": 58555
        },
        {
            "@id": "https://dch.iii.u-tokyo.ac.jp/api/media/58556",
            "o:id": 58556
        },
        {
            "@id": "https://dch.iii.u-tokyo.ac.jp/api/media/58557",
            "o:id": 58557
        },
        {
            "@id": "https://dch.iii.u-tokyo.ac.jp/api/media/58558",
            "o:id": 58558
        },
        {
            "@id": "https://dch.iii.u-tokyo.ac.jp/api/media/58559",
            "o:id": 58559
        }
    ],
    "o:modified": {
        "@type": "http://www.w3.org/2001/XMLSchema#dateTime",
        "@value": "2020-11-20T02:23:14+00:00"
    },
    "o:owner": {
        "@id": "https://dch.iii.u-tokyo.ac.jp/api/users/2",
        "o:id": 2
    },
    "o:resource_class": {
        "@id": "https://dch.iii.u-tokyo.ac.jp/api/resource_classes/110",
        "o:id": 110
    },
    "o:resource_template": {
        "@id": "https://dch.iii.u-tokyo.ac.jp/api/resource_templates/3",
        "o:id": 3
    },
    "o:site": [
        {
            "@id": "https://dch.iii.u-tokyo.ac.jp/api/sites/4",
            "o:id": 4
        },
        {
            "@id": "https://dch.iii.u-tokyo.ac.jp/api/sites/8",
            "o:id": 8
        }
    ],
    "o:thumbnail": null,
    "o:title": "日刊新聞興信所報 1117号",
    "ore:isAggregatedBy": [
        {
            "@id": "https://dch.iii.u-tokyo.ac.jp/api/items/53491",
            "display_title": "日刊新聞興信所報",
            "is_public": true,
            "property_id": 346,
            "property_label": "Is Aggregated By",
            "type": "resource",
            "url": null,
            "value_resource_id": 53491,
            "value_resource_name": "items"
        }
    ],
    "rdfs:seeAlso": [
        {
            "@id": "https://dch.iii.u-tokyo.ac.jp/api/items/56365",
            "is_public": true,
            "property_id": 342,
            "property_label": "seeAlso",
            "type": "uri"
        }
    ],
    "sc:viewingDirection": [
        {
            "@id": "http://iiif.io/api/presentation/2#rightToLeftDirection",
            "is_public": true,
            "property_id": 258,
            "property_label": "viewingDirection",
            "type": "uri"
        }
    ],
    "thumbnail_display_urls": {
        "large": "https://dch.iii.u-tokyo.ac.jp/files/large/c6cf6f3ab5d6945dd36b1f80cc6cce6a70340eba.jpg",
        "medium": "https://dch.iii.u-tokyo.ac.jp/files/medium/c6cf6f3ab5d6945dd36b1f80cc6cce6a70340eba.jpg",
        "square": "https://dch.iii.u-tokyo.ac.jp/files/square/c6cf6f3ab5d6945dd36b1f80cc6cce6a70340eba.jpg"
    },
    "uterms:manifestUri": [
        {
            "@id": "https://dch.iii.u-tokyo.ac.jp/iiif/97933bca-e47a-4a65-8d9f-26b6e1163b8e/manifest",
            "is_public": true,
            "property_id": 2843,
            "property_label": "Manifest Uri",
            "type": "uri"
        }
    ]
}